xonox/__init__.py
xonox/__main__.py
xonox/config.py
xonox/preset.py
xonox/preset_repository.py
xonox/preset_service.py
xonox/server.py
xonox/station.py
xonox/station_repository.py
xonox-1.1.0.dist-info/LICENSE
xonox-1.1.0.dist-info/METADATA
xonox-1.1.0.dist-info/WHEEL
xonox-1.1.0.dist-info/RECORD
