Metadata-Version: 2.1
Name: xonox
Version: 1.1.0
Summary: An alternative infrastructure-service for legacy NOXON(tm) devices
Home-page: https://github.com/x789/xonox
License: AGPL-3.0-only
Author: TillW 
Requires-Python: >=3.9,<4.0
Classifier: Development Status :: 5 - Production/Stable
Classifier: License :: OSI Approved :: GNU Affero General Public License v3
Classifier: Operating System :: OS Independent
Classifier: Programming Language :: Python :: 3
Classifier: Programming Language :: Python :: 3.9
Classifier: Programming Language :: Python :: 3.10
Classifier: Programming Language :: Python :: 3.11
Classifier: Programming Language :: Python :: 3.12
Requires-Dist: flask (>=3.0.0,<4.0.0)
Project-URL: Bug Tracker, https://github.com/x789/xonox/issues
Project-URL: Repository, https://github.com/x789/xonox
